nlpcode/__init__.py
nlpcode/answer.py
Nlp_Code-0.1.dist-info/METADATA
Nlp_Code-0.1.dist-info/WHEEL
Nlp_Code-0.1.dist-info/top_level.txt
Nlp_Code-0.1.dist-info/RECORD
