Metadata-Version: 2.1
Name: Nlp-Code
Version: 0.1
Summary: A short description of the package
Home-page: https://github.com/naveendgp/NlpCode
Author: Naveen Sakthi
Author-email: naveendgp@gmail.com
Classifier: Programming Language :: Python :: 3
Classifier: License :: OSI Approved :: MIT License
Classifier: Operating System :: OS Independent
Requires-Python: >=3.6
